setup.py
django_pdb/__init__.py
django_pdb/middleware.py
django_pdb/models.py
django_pdb/testrunners.py
django_pdb/utils.py
django_pdb.egg-info/PKG-INFO
django_pdb.egg-info/SOURCES.txt
django_pdb.egg-info/dependency_links.txt
django_pdb.egg-info/top_level.txt
django_pdb/management/__init__.py
django_pdb/management/commands/__init__.py
django_pdb/management/commands/runserver.py
django_pdb/management/commands/test.py