Metadata-Version: 1.0
Name: django-pdb
Version: 0.2.1
Summary: Gives you `manage.py runserver --pdb` and `manage.py test --pdb`
Home-page: https://github.com/tomchristie/django-pdb
Author: Tom Christie
Author-email: tom@tomchristie.com
License: Public Domain
Platform: UNKNOWN
Classifier: Programming Language :: Python
Classifier: Development Status :: 3 - Alpha
Classifier: Intended Audience :: Developers
Classifier: License :: Public Domain
Classifier: Framework :: Django
Classifier: Operating System :: OS Independent
